odoo10_addon_sale_automatic_workflow_exception-10.0.1.0.1-py3.8-nspkg.pth
odoo/addons/sale_automatic_workflow_exception/README.rst
odoo/addons/sale_automatic_workflow_exception/__init__.py
odoo/addons/sale_automatic_workflow_exception/__manifest__.py
odoo/addons/sale_automatic_workflow_exception/automatic_workflow_process.py
odoo/addons/sale_automatic_workflow_exception/i18n/ca.po
odoo/addons/sale_automatic_workflow_exception/i18n/de.po
odoo/addons/sale_automatic_workflow_exception/i18n/es.po
odoo/addons/sale_automatic_workflow_exception/i18n/fr.po
odoo/addons/sale_automatic_workflow_exception/i18n/sale_automatic_workflow_exception.pot
odoo/addons/sale_automatic_workflow_exception/i18n/sl.po
odoo/addons/sale_automatic_workflow_exception/i18n/tr_TR.po
odoo/addons/sale_automatic_workflow_exception/static/description/icon.png
odoo/addons/sale_automatic_workflow_exception/tests/__init__.py
odoo/addons/sale_automatic_workflow_exception/tests/test_automatic_workflow_exception.py
odoo10_addon_sale_automatic_workflow_exception-10.0.1.0.1.dist-info/METADATA
odoo10_addon_sale_automatic_workflow_exception-10.0.1.0.1.dist-info/WHEEL
odoo10_addon_sale_automatic_workflow_exception-10.0.1.0.1.dist-info/namespace_packages.txt
odoo10_addon_sale_automatic_workflow_exception-10.0.1.0.1.dist-info/top_level.txt
odoo10_addon_sale_automatic_workflow_exception-10.0.1.0.1.dist-info/RECORD
